{"edges":[["A","E"],["B","F"],["C","H"],["D","G"]],"tile#":0}
{"edges":[["A","E"],["B","F"],["C","G"],["D","H"]],"tile#":1}
{"edges":[["A","F"],["B","E"],["C","H"],["D","G"]],"tile#":2}
{"edges":[["A","E"],["B","D"],["C","G"],["F","H"]],"tile#":3}
{"edges":[["A","H"],["B","C"],["D","E"],["F","G"]],"tile#":4}
{"edges":[["A","E"],["B","C"],["D","H"],["F","G"]],"tile#":5}
{"edges":[["A","E"],["B","C"],["D","G"],["F","H"]],"tile#":6}
{"edges":[["A","D"],["B","G"],["C","F"],["E","H"]],"tile#":7}
{"edges":[["A","D"],["B","F"],["C","G"],["E","H"]],"tile#":8}
{"edges":[["A","D"],["B","E"],["C","H"],["F","G"]],"tile#":9}
{"edges":[["A","D"],["B","E"],["C","G"],["F","H"]],"tile#":10}
{"edges":[["A","D"],["B","C"],["E","H"],["F","G"]],"tile#":11}
{"edges":[["A","C"],["B","H"],["D","F"],["E","G"]],"tile#":12}
{"edges":[["A","C"],["B","H"],["D","E"],["F","G"]],"tile#":13}
{"edges":[["A","C"],["B","G"],["D","F"],["E","H"]],"tile#":14}
{"edges":[["A","C"],["B","G"],["D","E"],["F","H"]],"tile#":15}
{"edges":[["A","C"],["B","F"],["D","H"],["E","G"]],"tile#":16}
{"edges":[["A","C"],["B","F"],["D","G"],["E","H"]],"tile#":17}
{"edges":[["A","C"],["B","E"],["D","H"],["F","G"]],"tile#":18}
{"edges":[["A","C"],["B","E"],["D","G"],["F","H"]],"tile#":19}
{"edges":[["A","C"],["B","D"],["E","H"],["F","G"]],"tile#":20}
{"edges":[["A","C"],["B","D"],["E","G"],["F","H"]],"tile#":21}
{"edges":[["A","B"],["C","H"],["D","G"],["E","F"]],"tile#":22}
{"edges":[["A","B"],["C","H"],["D","F"],["E","G"]],"tile#":23}
{"edges":[["A","B"],["C","H"],["D","E"],["F","G"]],"tile#":24}
{"edges":[["A","B"],["C","G"],["D","H"],["E","F"]],"tile#":25}
{"edges":[["A","B"],["C","G"],["D","F"],["E","H"]],"tile#":26}
{"edges":[["A","B"],["C","G"],["D","E"],["F","H"]],"tile#":27}
{"edges":[["A","B"],["C","F"],["D","H"],["E","G"]],"tile#":28}
{"edges":[["A","B"],["C","F"],["D","G"],["E","H"]],"tile#":29}
{"edges":[["A","B"],["C","E"],["D","H"],["F","G"]],"tile#":30}
{"edges":[["A","B"],["C","E"],["D","G"],["F","H"]],"tile#":31}
{"edges":[["A","B"],["C","D"],["E","H"],["F","G"]],"tile#":32}
{"edges":[["A","B"],["C","D"],["E","G"],["F","H"]],"tile#":33}
{"edges":[["A","B"],["C","D"],["E","F"],["G","H"]],"tile#":34}
